MANIFEST.in
README.txt
requirements.txt
setup.py
saucelabsfixture/__init__.py
saucelabsfixture/connect.py
saucelabsfixture/ondemand.py
saucelabsfixture/sst.py
saucelabsfixture/utils.py
saucelabsfixture.egg-info/PKG-INFO
saucelabsfixture.egg-info/SOURCES.txt
saucelabsfixture.egg-info/dependency_links.txt
saucelabsfixture.egg-info/not-zip-safe
saucelabsfixture.egg-info/requires.txt
saucelabsfixture.egg-info/top_level.txt