Metadata-Version: 1.0
Name: saucelabsfixture
Version: 0.1
Summary: A fixture for working with SauceLabs' services.
Home-page: UNKNOWN
Author: UNKNOWN
Author-email: UNKNOWN
License: UNKNOWN
Platform: UNKNOWN
